starbot_executor/__init__.py
starbot_executor/core/__init__.py
starbot_executor/core/executor.py
starbot_executor-1.4.0.dist-info/LICENSE
starbot_executor-1.4.0.dist-info/METADATA
starbot_executor-1.4.0.dist-info/WHEEL
starbot_executor-1.4.0.dist-info/RECORD
