Metadata-Version: 2.1
Name: starbot-executor
Version: 1.4.0
Summary: 一个基于订阅发布模式的异步执行器
Home-page: https://github.com/Starlwr/StarBotExecutor
License: MIT
Keywords: starbot,async,executor
Author: Starlwr
Author-email: lwr1104@qq.com
Requires-Python: >=3.10,<4.0
Classifier: License :: OSI Approved :: MIT License
Classifier: Programming Language :: Python :: 3
Classifier: Programming Language :: Python :: 3.10
Classifier: Programming Language :: Python :: 3.11
Project-URL: Repository, https://github.com/Starlwr/StarBotExecutor
